{
  "generator-jhipster": {
    "applicationType": "monolith",
    "baseName": "Blogger_WebApp",
    "jhipsterVersion": "7.3.1",
    "skipClient": false,
    "skipServer": false,
    "skipUserManagement": false,
    "skipCheckLengthOfIdentifier": false,
    "skipFakeData": false,
    "jhiPrefix": "jhi",
    "entitySuffix": "",
    "dtoSuffix": "DTO",
    "testFrameworks": [],
    "blueprints": [],
    "otherModules": [],
    "pages": [],
    "creationTimestamp": 1635792510621,
    "serviceDiscoveryType": "no",
    "reactive": false,
    "authenticationType": "jwt",
    "packageName": "com.example.blogger",
    "serverPort": "8080",
    "cacheProvider": "ehcache",
    "enableHibernateCache": true,
    "databaseType": "sql",
    "devDatabaseType": "h2Disk",
    "prodDatabaseType": "postgresql",
    "buildTool": "maven",
    "serverSideOptions": [],
    "websocket": false,
    "searchEngine": false,
    "messageBroker": false,
    "enableSwaggerCodegen": false,
    "clientFramework": "angularX",
    "withAdminUi": true,
    "clientTheme": "none",
    "enableTranslation": false,
    "nativeLanguage": "en",
    "jwtSecretKey": "ZjgwN2U3ZDIyYWZkMzNhZmJkOTA1YWJjMWUwNmQ5YjkyOTVkN2ViZWI0NWQ3NDQ5NzJiYjFmNTQxODI3ZjYzODczNGJhYjJkZmMwZjk5NmUxMzNlY2QzYmQ5NDlkODcxOTg2ODY2YzBmYmE5NGNkZTMxOTYwODc2MmM1OGNhNWU=",
    "devServerPort": 4200,
    "clientPackageManager": "npm",
    "clientThemeVariant": "",
    "enableGradleEnterprise": false,
    "languages": ["en", "fr"]
  }
}
